lbfgs_lab/__init__.py
lbfgs_lab/LBFGS/README.md
lbfgs_lab/LBFGS/_callback.py
lbfgs_lab/LBFGS/_lineSearch.py
lbfgs_lab/LBFGS/_objectiveFunction.py
lbfgs_lab/LBFGS/_params.py
lbfgs_lab/LBFGS/_retValues.py
lbfgs_lab/LBFGS/_utils.py
lbfgs_lab/LBFGS/lbfgs.py
lbfgs_lab-0.0.2.dist-info/METADATA
lbfgs_lab-0.0.2.dist-info/WHEEL
lbfgs_lab-0.0.2.dist-info/licenses/LICENSE
lbfgs_lab-0.0.2.dist-info/RECORD
