Metadata-Version: 2.4
Name: lbfgs_lab
Version: 0.0.2
Summary: L-BFGS variants for academic research
Project-URL: Homepage, https://github.com/HirokiHamaguchi/lbfgs_lab
Project-URL: Issues, https://github.com/HirokiHamaguchi/lbfgs_lab/issues
Author-email: Hiroki Hamaguchi <hari64boli64@gmail.com>
License-Expression: MIT
License-File: LICENSE
Classifier: Operating System :: OS Independent
Classifier: Programming Language :: Python :: 3
Requires-Python: >=3.8
